ysql/__init__.py
ysql/dao.py
ysql/database.py
ysql/entity.py
ysql-1.5.0.dist-info/LICENSE.txt
ysql-1.5.0.dist-info/METADATA
ysql-1.5.0.dist-info/WHEEL
ysql-1.5.0.dist-info/top_level.txt
ysql-1.5.0.dist-info/RECORD
