Metadata-Version: 2.1
Name: ysql
Version: 1.5.0
Summary: a more efficient and concise SQLite framework.
Home-page: https://gitee.com/darlingxyz/ysql
Author: dfqxhhh
Author-email: dfqxhhh@163.com
Classifier: Programming Language :: Python :: 3
Classifier: License :: OSI Approved :: MIT License
Classifier: Operating System :: OS Independent
License-File: LICENSE.txt
